{
    "Shrimp Taming Bait": "https://wiki.mabinogiworld.com/view/Shrimp_Taming_Bait",
    "Shyllien": "https://wiki.mabinogiworld.com/view/Shyllien",
    "Magic Parchment": "https://wiki.mabinogiworld.com/view/Magic_Parchment",
    "Tough String": "https://wiki.mabinogiworld.com/view/Tough_String",
    "Hillwen Alloy": "https://wiki.mabinogiworld.com/view/Hillwen_Alloy",
    "Wheat Flour": "https://wiki.mabinogiworld.com/view/Wheat_Flour",
    "Spin Gear": "https://wiki.mabinogiworld.com/view/Spin_Gear",
    "Average Firewood": "https://wiki.mabinogiworld.com/view/Average_Firewood",
    "Fine Silk": "https://wiki.mabinogiworld.com/view/Fine_Silk",
    "Energy Amplifier": "https://wiki.mabinogiworld.com/view/Energy_Amplifier",
    "Sturdy Loop": "https://wiki.mabinogiworld.com/view/Sturdy_Loop",
    "Magic Quill Pen": "https://wiki.mabinogiworld.com/view/Magic_Quill_Pen",
    "Stamina 500 Potion": "https://wiki.mabinogiworld.com/view/Stamina_500_Potion",
    "Braid": "https://wiki.mabinogiworld.com/view/Braid",
    "Cotton Cushion Stuffing": "https://wiki.mabinogiworld.com/view/Cotton_Cushion_Stuffing",
    "Finest Silk": "https://wiki.mabinogiworld.com/view/Finest_Silk",
    "Finest Leather Strap": "https://wiki.mabinogiworld.com/view/Finest Leather_Strap",
    "Tough Thread": "https://wiki.mabinogiworld.com/view/Tough_Thread",
    "Spirit Liqueur": "https://wiki.mabinogiworld.com/view/Spirit_Liqueur",
    "Silver Plate": "https://wiki.mabinogiworld.com/view/Silver_Plate",
    "Fine Fabric": "https://wiki.mabinogiworld.com/view/Fine_Fabric",
    "Pet Playset": "https://wiki.mabinogiworld.com/view/Pet_Playset",
    "Hay Bale": "https://wiki.mabinogiworld.com/view/Hay_Bale",
    "Enchanted Firewood": "https://wiki.mabinogiworld.com/view/Enchanted_Firewood",
    "MP 500 Potion": "https://wiki.mabinogiworld.com/view/MP_500_Potion",
    "Fine Firewood": "https://wiki.mabinogiworld.com/view/Fine_Firewood",
    "Purified Rabbit Foot": "https://wiki.mabinogiworld.com/view/Purified_Rabbit_Foot",
    "Energy Converter": "https://wiki.mabinogiworld.com/view/Energy_Converter",
    "Sundew": "https://wiki.mabinogiworld.com/view/Sundew",
    "Finest Vanilla Scented Candle": "https://wiki.mabinogiworld.com/view/Finest_Vanilla_Scented_Candle",
    "Artificial Turf": "https://wiki.mabinogiworld.com/view/Artificial Turf",
    "Emerald Fuse": "https://wiki.mabinogiworld.com/view/Emerald_Fuse",
    "Fine Leather Strap": "https://wiki.mabinogiworld.com/view/Fine_Leather_Strap",
    "Mythril Nail": "https://wiki.mabinogiworld.com/view/Large_Mythril_Nail",
    "Poison Tip Wyvern Ballista": "https://wiki.mabinogiworld.com/view/Poison_Tip_Wyvern_Ballista_Bolt",
    "Finest Firewood": "https://wiki.mabinogiworld.com/view/Finest_Firewood",
    "Copper Plate": "https://wiki.mabinogiworld.com/view/Copper_Plate",
    "Mysterious Herb Powder": "https://wiki.mabinogiworld.com/view/Mysterious_Herb_Powder",
    "Mythril Plate": "https://wiki.mabinogiworld.com/view/Mythril_Plate",
    "Barley Flour": "https://wiki.mabinogiworld.com/view/Barley_Flour",
    "Marionette 500 Potion": "https://wiki.mabinogiworld.com/view/Marionette_500_Potion",
    "Gold Plate": "https://wiki.mabinogiworld.com/view/Gold_Plate",
    "Glittering Paper": "https://wiki.mabinogiworld.com/view/Glittering_Paper",
    "Finest Fabric": "https://wiki.mabinogiworld.com/view/Finest_Fabric",
    "HP 500 Potion": "https://wiki.mabinogiworld.com/view/HP_500_Potion",
    "Mutant": "https://wiki.mabinogiworld.com/view/Mutant",
    "Harmonious Cosmos Perfume": "https://wiki.mabinogiworld.com/view/Harmonious_Cosmos_Perfume",
    "Special Firewood": "https://wiki.mabinogiworld.com/view/Special_Firewood"
}